toomanycells/__init__.py
toomanycells/cellAnnotation.py
toomanycells/common.py
toomanycells/multiPlotter.py
toomanycells/similarityMatrix.py
toomanycells/tmcGraph.py
toomanycells/tmcHaskell.py
toomanycells/toomanycells.py
toomanycells/data/metadata.csv
toomanycells-1.0.69.dist-info/licenses/LICENSE
toomanycells-1.0.69.dist-info/METADATA
toomanycells-1.0.69.dist-info/WHEEL
toomanycells-1.0.69.dist-info/entry_points.txt
toomanycells-1.0.69.dist-info/top_level.txt
toomanycells-1.0.69.dist-info/RECORD
