Metadata-Version: 2.4
Name: toomanycells
Version: 1.0.69
Summary: A python package for spectral clustering.
Author-email: Javier Ruiz-Ramirez <javier.ruizramirez@uhn.ca>
License: BSD License
Project-URL: Homepage, https://github.com/JRR3/toomanycells
Keywords: toomanycells
Classifier: Intended Audience :: Developers
Classifier: Natural Language :: English
Classifier: Programming Language :: Python :: 3.9
Classifier: Programming Language :: Python :: 3.10
Classifier: Programming Language :: Python :: 3.11
Classifier: Programming Language :: Python :: 3.12
Requires-Python: >=3.9
License-File: LICENSE
Requires-Dist: scanpy
Requires-Dist: scipy
Requires-Dist: numpy
Requires-Dist: pandas
Requires-Dist: networkx
Requires-Dist: tqdm
Requires-Dist: scikit-learn
Requires-Dist: matplotlib
Requires-Dist: plotly
Requires-Dist: celltypist
Provides-Extra: all
Requires-Dist: toomanycells[extra]; extra == "all"
Provides-Extra: extra
Dynamic: license-file
